DLD/CA1/test.sv
module oia1(input a,b,c, output w);
// supply1 vdd;
// supply0 gdd;
// wire y1, y2;
// pmos p1(y2, vdd, a), p2(w, y2, b), p3(w, vdd, c);
// nmos n1(y1, gdd, a), n2(y1, gdd, b), n3(w, y1, c);
assign w = ~((a|b)&c);
// #(6,7,8) #(3,4,5)
endmodule

DLD/CA1/ht.v
`timescale 1ns/1ns
`include "test.sv"
module ht();
reg a,b =1,c=0;
wire w;
oia1 uut(a,b,c,w);
initial repeat(5)#7 c = ~c;
initial repeat(3)#11 b = ~b;
initial begin
    $dumpfile("ht.vcd");
    $dumpvars(0, ht);
    a =0;
    repeat(4)#9 a = ~a;
    $display("test complate");
end
endmodule

DLD/CA1/ht.vcd
$date
	Sun Apr 10 12:35:58 2022
$end
$version
	Icarus Verilog
$end
$timescale
	1ns
$end
$scope module ht $end
$var wire 1 ! w $end
$var reg 1 " a $end
$var reg 1 # b $end
$var reg 1 $ c $end
$scope module uut $end
$var wire 1 " a $end
$var wire 1 # b $end
$var wire 1 $ c $end
$var wire 1 ! w $end
$upscope $end
$upscope $end
$enddefinitions $end
#0
$dumpvars
0$
1#
0"
1!
$end
#7
0!
1$
#9
1"
#11
0#
#14
1!
0$
#18
0"
#21
1$
#22
0!
1#
#27
1"
#28
1!
0$
#33
0#
#35
0!
1$
#36
1!
0"
