DLD/CA1/NOR.v
module NOR(input a,b, output w);
    supply1 vdd;
    supply0 gdd;
    wire y1;
    pmos #(5,6,7) p1(y1, vdd, a), p2(w, y1, b);
    nmos #(3,4,5) n1(w, gdd, a), n2(w, gdd, b);
endmodule

DLD/CA1/NORT.v
`timescale 1ns/1ns
`include "NOR.v"
module NORT();
    reg a=0, b=0;
    wire w;
    NOR uut(a,b,w);
    initial repeat(13)#100 a = ~a;
    initial begin
        $dumpfile("NORT.vcd");
        $dumpvars(0, NORT);
        repeat(5)#220b = ~b;
    end
endmodule

DLD/CA1/NORT.vcd
$d
	Wed Mar  9 23:12:54 2022
$end
$version
	Icarus Verilog
$end
$timescale
	1ns
$end
$scope module NORT $end
$var wire 1 ! w $end
$var reg 1 " a $end
$var reg 1 # b $end
$scope module uut $end
$var wire 1 " a $end
$var wire 1 # b $end
$var wire 1 $ gdd $end
$var wire 1 % vdd $end
$var wire 1 ! w $end
$var wire 1 & y1 $end
$upscope $end
$upscope $end
$enddefinitions $end
#0
$dumpvars
x&
1%
0$
0#
0"
x!
$end
#5
x!
1&
#10
1!
#100
1"
#104
x!
#107
z&
#114
0!
#200
0"
#205
1&
z!
#210
1!
#220
1#
#224
x!
#227
0!
#300
1"
#307
z&
#400
0"
#405
1&
#440
0#
#445
1!
#500
1"
#504
x!
#507
z&
#514
0!
#600
0"
#605
1&
z!
#610
1!
#660
1#
#664
x!
#667
0!
#700
1"
#707
z&
#800
0"
#805
1&
#880
0#
#885
1!
#900
1"
#904
x!
#907
z&
#914
0!
#1000
0"
#1005
1&
z!
#1010
1!
#1100
1"
1#
#1104
x!
#1107
z&
0!
#1200
0"
#1205
1&
#1300
1"
#1307
z&
