DLD/CA1/NOT.v
module NOT(input a, output w);
    supply1 vdd;
    supply0 gdd;
    pmos #(5,6,7) p1(w, vdd, a);
    nmos #(3,4,5) n1(w, gdd, a);
endmodule

DLD/CA1/NOTT.v
`timescale 1ns/1ns
`include "NOT.v"
module NOTT();
    reg a = 0;
    wire w;
    NOT n(a,w);
    initial begin
        $dumpfile("NOTT.vcd");
        $dumpvars(0, NOTT);
        repeat(5)#20 a = ~a;
    end
endmodule

DLD/CA1/NOTT.vcd
$d
	Thu May 26 15:46:02 2022
$end
$version
	Icarus Verilog
$end
$timescale
	1ns
$end
$scope module NOTT $end
$var wire 1 ! w $end
$var reg 1 " a $end
$scope module n $end
$var wire 1 " a $end
$var wire 1 # gdd $end
$var wire 1 $ vdd $end
$var wire 1 ! w $end
$upscope $end
$upscope $end
$enddefinitions $end
#0
$dumpvars
1$
0#
0"
x!
$end
#5
1!
#20
1"
#24
x!
#27
0!
#40
0"
#45
1!
#60
1"
#64
x!
#67
0!
#80
0"
#85
1!
#100
1"
#104
x!
#107
0!
